<?xml version="1.0" encoding="UTF-8" ?>
<!DOCTYPE mapper PUBLIC "-//mybatis.org//DTD Mapper 3.0//EN" "http://mybatis.org/dtd/mybatis-3-mapper.dtd" >
<mapper namespace="com.jml.serviceapi.dao.OauthRefreshTokenMapper" >
  <resultMap id="BaseResultMap" type="com.jml.serviceapi.dto.OauthRefreshToken" >
    <!--
      WARNING - @mbggenerated
      This element is automatically generated by MyBatis Generator, do not modify.
    -->
    <result column="token_id" property="tokenId" jdbcType="VARCHAR" />
    <result column="token" property="token" jdbcType="LONGVARBINARY" />
    <result column="authentication" property="authentication" jdbcType="LONGVARBINARY" />
  </resultMap>
  <insert id="insert" parameterType="com.jml.serviceapi.dto.OauthRefreshToken" >
    <!--
      WARNING - @mbggenerated
      This element is automatically generated by MyBatis Generator, do not modify.
    -->
    insert into oauth_refresh_token (token_id, token, authentication
      )
    values (#{tokenId,jdbcType=VARCHAR}, #{token,jdbcType=LONGVARBINARY}, #{authentication,jdbcType=LONGVARBINARY}
      )
  </insert>
  <select id="selectAll" resultMap="BaseResultMap" >
    <!--
      WARNING - @mbggenerated
      This element is automatically generated by MyBatis Generator, do not modify.
    -->
    select token_id, token, authentication
    from oauth_refresh_token
  </select>
</mapper>